OSDetect.py
osdetect-1.2.1.dist-info/METADATA
osdetect-1.2.1.dist-info/WHEEL
osdetect-1.2.1.dist-info/licenses/LICENSE
osdetect-1.2.1.dist-info/RECORD
