Metadata-Version: 2.4
Name: OSDetect
Version: 1.2.1
Summary: A simple helper module to get details on the current operating system platorm.
Project-URL: Homepage, https://malte70.github.io/OSDetect/
Project-URL: Repository, https://github.com/malte70/OSDetect
Project-URL: Issues, https://github.com/malte70/OSDetect/issues
Author: Malte Bublitz
License-Expression: MIT
License-File: LICENSE
Classifier: Development Status :: 4 - Beta
Classifier: Intended Audience :: Developers
Classifier: License :: OSI Approved :: MIT License
Classifier: Operating System :: MacOS :: MacOS X
Classifier: Operating System :: Microsoft :: Windows
Classifier: Operating System :: POSIX :: Linux
Classifier: Programming Language :: Python
Classifier: Topic :: Software Development :: Libraries :: Python Modules
Requires-Python: >=3.8
